ParTree/__init__.py
ParTree/algorithms/__init__.py
ParTree/algorithms/bic_estimator.py
ParTree/algorithms/data_splitter.py
ParTree/classes/CenterParTree.py
ParTree/classes/CenterParTree2.py
ParTree/classes/ImpurityParTree.py
ParTree/classes/ImpurityParTree2.py
ParTree/classes/ParTree.py
ParTree/classes/ParTree_node.py
ParTree/classes/PrincipalParTree.py
ParTree/classes/__init__.py
ParTree-0.0.1.dist-info/LICENSE
ParTree-0.0.1.dist-info/METADATA
ParTree-0.0.1.dist-info/WHEEL
ParTree-0.0.1.dist-info/top_level.txt
ParTree-0.0.1.dist-info/RECORD
